apimd/__init__.py
apimd/__main__.py
apimd/loader.py
apimd/logger.py
apimd/parser.py
apimd/pep585.py
apimd/py.typed
apimd-2.1.1.dist-info/LICENSE
apimd-2.1.1.dist-info/METADATA
apimd-2.1.1.dist-info/WHEEL
apimd-2.1.1.dist-info/entry_points.txt
apimd-2.1.1.dist-info/top_level.txt
apimd-2.1.1.dist-info/RECORD
