Metadata-Version: 2.1
Name: apimd
Version: 2.1.1
Summary: A Python API compiler for universal Markdown syntax.
Home-page: https://github.com/KmolYuan/apimd
Author: Yuan Chang
Author-email: pyslvs@gmail.com
License: MIT
Keywords: Markdown,API
Platform: UNKNOWN
Classifier: Programming Language :: Python :: 3.9
Classifier: Topic :: Documentation
Classifier: Topic :: Utilities
Classifier: Environment :: Console
Classifier: Operating System :: OS Independent
Classifier: Typing :: Typed
Requires-Python: >=3.9
Requires-Dist: colorlog
